[  
   {  
      "id":"20160118_PocketGamerConnects",
      "name":"Pocket Gamer Connects",
      "description":"Description: Pocket Gamer Connects",
      "technologies":"Android",
      "link":"http://www.pgconnects.com/london/",
      "attendees":1100,
      "country":"UK",
      "city":"London",
      "timestamp_start":1453071600,
      "timestamp_end":1453071600,
      "human_date_start":"18 Jan 2016",
      "human_date_end":"18 Jan 2016"
   },
   {  
      "id":"20160128_VoXXedDays",
      "name":"VoXXed Days",
      "description":"Description: VoXXed Days",
      "technologies":"Mobile Web (Create/Make your website mobile friendly)",
      "link":"https://voxxeddays.com/berlin/",
      "attendees":300,
      "country":"Germany",
      "city":"Berlin",
      "timestamp_start":1453935600,
      "timestamp_end":1453935600,
      "human_date_start":"28 Jan 2016",
      "human_date_end":"28 Jan 2016"
   },
   {  
      "id":"20160201_OOP",
      "name":"OOP",
      "description":"Description: OOP",
      "technologies":"IoT",
      "link":"http://www.oop-konferenz.de/",
      "attendees":2000,
      "country":"Germany",
      "city":"Munich",
      "timestamp_start":1454281200,
      "timestamp_end":1454281200,
      "human_date_start":"1 Feb 2016",
      "human_date_end":"1 Feb 2016"
   },
   {  
      "id":"20160210_IOTTechExpoEurope",
      "name":"IOT Tech Expo Europe",
      "description":"Description: IOT Tech Expo Europe",
      "technologies":"IoT",
      "link":"http://www.iottechexpo.com/europe/",
      "attendees":5000,
      "country":"UK",
      "city":"London",
      "timestamp_start":1455058800,
      "timestamp_end":1455058800,
      "human_date_start":"10 Feb 2016",
      "human_date_end":"10 Feb 2016"
   },
   {  
      "id":"20160217_MobileTrendsConference",
      "name":"Mobile Trends Conference",
      "description":"Description: Mobile Trends Conference",
      "technologies":"Play",
      "link":"http://2016.mobiletrends.pl/en/",
      "attendees":400,
      "country":"Poland",
      "city":"Krakow",
      "timestamp_start":1455663600,
      "timestamp_end":1455663600,
      "human_date_start":"17 Feb 2016",
      "human_date_end":"17 Feb 2016"
   },
   {  
      "id":"20160218_CasualConnect",
      "name":"Casual Connect",
      "description":"Description: Casual Connect",
      "technologies":"Android",
      "link":"https://goo.gl/KxGD0p",
      "attendees":500,
      "country":"Netherlands",
      "city":"Amsterdam",
      "timestamp_start":1455750000,
      "timestamp_end":1455750000,
      "human_date_start":"18 Feb 2016",
      "human_date_end":"18 Feb 2016"
   },
   {  
      "id":"20160222_MobileWorldCongress2016",
      "name":"Mobile World Congress 2016",
      "description":"Description: Mobile World Congress 2016",
      "technologies":"Android",
      "link":"mobileworldcongress.com",
      "attendees":"",
      "country":"Spain",
      "city":"Barcelona",
      "timestamp_start":1456095600,
      "timestamp_end":1456095600,
      "human_date_start":"22 Feb 2016",
      "human_date_end":"22 Feb 2016"
   },
   {  
      "id":"20160225_BigDataTechnologySummit",
      "name":"Big Data Technology Summit",
      "description":"Description: Big Data Technology Summit",
      "technologies":"Cloud",
      "link":"http://bigdatatech.pl/en/",
      "attendees":200,
      "country":"Poland",
      "city":"Warsaw",
      "timestamp_start":1456354800,
      "timestamp_end":1456354800,
      "human_date_start":"25 Feb 2016",
      "human_date_end":"25 Feb 2016"
   },
   {  
      "id":"20160301_WorldClassDigitalTransformation",
      "name":"World Class Digital Transformation",
      "description":"Description: World Class Digital Transformation",
      "technologies":"IoT",
      "link":"https://www.manetch.com/events/wcdgt",
      "attendees":"",
      "country":"Germany",
      "city":"Frankfurt-Darmstadt",
      "timestamp_start":1456786800,
      "timestamp_end":1456786800,
      "human_date_start":"1 Mar 2016",
      "human_date_end":"1 Mar 2016"
   },
   {  
      "id":"20160307_QconLondon",
      "name":"Qcon London",
      "description":"Description: Qcon London",
      "technologies":"Chrome",
      "link":"http://qconlondon.com/",
      "attendees":1200,
      "country":"UK",
      "city":"London",
      "timestamp_start":1457305200,
      "timestamp_end":1457305200,
      "human_date_start":"7 Mar 2016",
      "human_date_end":"7 Mar 2016"
   },
   {  
      "id":"20160310_FrankfurterEntwicklertag",
      "name":"Frankfurter Entwicklertag",
      "description":"Description: Frankfurter Entwicklertag",
      "technologies":"Android",
      "link":"http://entwicklertag.de/frankfurt/2016/",
      "attendees":"",
      "country":"Germany",
      "city":"Frankfurt",
      "timestamp_start":1457564400,
      "timestamp_end":1457564400,
      "human_date_start":"10 Mar 2016",
      "human_date_end":"10 Mar 2016"
   },
   {  
      "id":"20160311_RITSIConference",
      "name":"RITSI Conference",
      "description":"Description: RITSI Conference",
      "technologies":"Android, Android TV, Cardboard, Cloud, Firebase, Material Design, Play Games, Other Google Technology, Open technologies (non-google)",
      "link":"https://goo.gl/PuZDFQ",
      "attendees":1500,
      "country":"Spain",
      "city":"Madrid",
      "timestamp_start":1457650800,
      "timestamp_end":1457650800,
      "human_date_start":"11 Mar 2016",
      "human_date_end":"11 Mar 2016"
   },
   {  
      "id":"20160314_IOTConferenceMunich",
      "name":"IOT Conference Munich",
      "description":"Description: IOT Conference Munich",
      "technologies":"IoT",
      "link":"https://iotcon.de/",
      "attendees":1000,
      "country":"Germany",
      "city":"Munich",
      "timestamp_start":1457910000,
      "timestamp_end":1457910000,
      "human_date_start":"14 Mar 2016",
      "human_date_end":"14 Mar 2016"
   },
   {  
      "id":"20160314_MobileTechConference",
      "name":"Mobile Tech Conference",
      "description":"Description: Mobile Tech Conference",
      "technologies":"Android",
      "link":"https://mobiletechcon.de/",
      "attendees":100,
      "country":"Germany",
      "city":"Munich",
      "timestamp_start":1457910000,
      "timestamp_end":1457910000,
      "human_date_start":"14 Mar 2016",
      "human_date_end":"14 Mar 2016"
   },
   {  
      "id":"20160314_MobileTechConferenceSpring",
      "name":"Mobile Tech Conference Spring",
      "description":"Description: Mobile Tech Conference Spring",
      "technologies":"Android",
      "link":"https://mobiletechcon.de/",
      "attendees":"",
      "country":"Germany",
      "city":"Munich",
      "timestamp_start":1457910000,
      "timestamp_end":1457910000,
      "human_date_start":"14 Mar 2016",
      "human_date_end":"14 Mar 2016"
   },
   {  
      "id":"20160317_Mdevcon2016",
      "name":"Mdevcon 2016",
      "description":"Description: Mdevcon 2016",
      "technologies":"Android",
      "link":"http://mdevcon.com/",
      "attendees":250,
      "country":"Netherlands",
      "city":"Amsterdam",
      "timestamp_start":1458169200,
      "timestamp_end":1458169200,
      "human_date_start":"17 Mar 2016",
      "human_date_end":"17 Mar 2016"
   },
   {  
      "id":"20160317_MobileDeveloperConference(MDevCon)2016",
      "name":"Mobile Developer Conference (MDevCon) 2016",
      "description":"Description: Mobile Developer Conference (MDevCon) 2016",
      "technologies":"Android, Firebase, Mobile Web ( Create/Make your website mobile friendly), Other Google Technology",
      "link":"https://goo.gl/wGhHxs",
      "attendees":300,
      "country":"Netherlands",
      "city":"Amsterdam",
      "timestamp_start":1458169200,
      "timestamp_end":1458169200,
      "human_date_start":"17 Mar 2016",
      "human_date_end":"17 Mar 2016"
   },
   {  
      "id":"20160318_CodemotionRome",
      "name":"Codemotion Rome",
      "description":"Description: Codemotion Rome",
      "technologies":"Android, Firebase",
      "link":"https://goo.gl/E26Myb",
      "attendees":2500,
      "country":"Italy",
      "city":"Rome",
      "timestamp_start":1458255600,
      "timestamp_end":1458255600,
      "human_date_start":"18 Mar 2016",
      "human_date_end":"18 Mar 2016"
   },
   {  
      "id":"20160318_CodemotionRome",
      "name":"Codemotion Rome",
      "description":"Description: Codemotion Rome",
      "technologies":"Android",
      "link":"rome2016.codemotionworld.com",
      "attendees":2000,
      "country":"Italy",
      "city":"Rome",
      "timestamp_start":1458255600,
      "timestamp_end":1458255600,
      "human_date_start":"18 Mar 2016",
      "human_date_end":"18 Mar 2016"
   },
   {  
      "id":"20160319_CloudConf",
      "name":"CloudConf",
      "description":"Description: CloudConf",
      "technologies":"Cloud, Firebase",
      "link":"https://goo.gl/TtljQ8",
      "attendees":500,
      "country":"Italy",
      "city":"Turin",
      "timestamp_start":1458342000,
      "timestamp_end":1458342000,
      "human_date_start":"19 Mar 2016",
      "human_date_end":"19 Mar 2016"
   },
   {  
      "id":"20160401_FronteersSpringConference",
      "name":"Fronteers Spring Conference",
      "description":"Description: Fronteers Spring Conference",
      "technologies":"Chrome, Firebase, Material Design, Other Google Technology",
      "link":"https://goo.gl/dZheSY",
      "attendees":300,
      "country":"Netherlands",
      "city":"Amsterdam",
      "timestamp_start":1459461600,
      "timestamp_end":1459461600,
      "human_date_start":"1 Apr 2016",
      "human_date_end":"1 Apr 2016"
   },
   {  
      "id":"20160406_IndustrialInternet",
      "name":"Industrial Internet",
      "description":"Description: Industrial Internet",
      "technologies":"IoT",
      "link":"http://www.smartsummit.net/frankfurt/industrial-internet-summit.html/",
      "attendees":1500,
      "country":"Germany",
      "city":"Frankfurt",
      "timestamp_start":1459893600,
      "timestamp_end":1459893600,
      "human_date_start":"6 Apr 2016",
      "human_date_end":"6 Apr 2016"
   },
   {  
      "id":"20160407_DisruptSpace",
      "name":"DisruptSpace",
      "description":"Description: DisruptSpace",
      "technologies":"Other Google Technology",
      "link":"http://disruptspace.io",
      "attendees":100,
      "country":"Germany",
      "city":"Bremen",
      "timestamp_start":1459980000,
      "timestamp_end":1459980000,
      "human_date_start":"7 Apr 2016",
      "human_date_end":"7 Apr 2016"
   },
   {  
      "id":"20160407_DroidconTurin",
      "name":"Droidcon Turin",
      "description":"Description: Droidcon Turin",
      "technologies":"Android",
      "link":"https://goo.gl/NTNJIn",
      "attendees":500,
      "country":"Italy",
      "city":"Turin",
      "timestamp_start":1459980000,
      "timestamp_end":1459980000,
      "human_date_start":"7 Apr 2016",
      "human_date_end":"7 Apr 2016"
   },
   {  
      "id":"20160407_DroidconTurin2016",
      "name":"Droidcon Turin 2016",
      "description":"Description: Droidcon Turin 2016",
      "technologies":"Android",
      "link":"http://it.droidcon.com/2016/",
      "attendees":800,
      "country":"Italy",
      "city":"Turin",
      "timestamp_start":1459980000,
      "timestamp_end":1459980000,
      "human_date_start":"7 Apr 2016",
      "human_date_end":"7 Apr 2016"
   },
   {  
      "id":"20160409_PioneersfestivalBremen(likely4/9/2016)",
      "name":"Pioneers festival Bremen (likely 4/9/2016)",
      "description":"Description: Pioneers festival Bremen (likely 4/9/2016)",
      "technologies":"Android",
      "link":"http://www.pioneersbremen.de/",
      "attendees":2500,
      "country":"Germany",
      "city":"Bremen",
      "timestamp_start":1460152800,
      "timestamp_end":1460152800,
      "human_date_start":"9 Apr 2016",
      "human_date_end":"9 Apr 2016"
   },
   {  
      "id":"20160411_N端rnbergWebWeek",
      "name":"N端rnberg Web Week",
      "description":"Description: N端rnberg Web Week",
      "technologies":"Android",
      "link":"http://nueww.de/",
      "attendees":1000,
      "country":"Germany",
      "city":"Nuremberg",
      "timestamp_start":1460325600,
      "timestamp_end":1460325600,
      "human_date_start":"11 Apr 2016",
      "human_date_end":"11 Apr 2016"
   },
   {  
      "id":"20160411_UXPoland",
      "name":"UX Poland",
      "description":"Description: UX Poland",
      "technologies":"Material Design",
      "link":"www.uxpoland.com",
      "attendees":400,
      "country":"Poland",
      "city":"Warsaw",
      "timestamp_start":1460325600,
      "timestamp_end":1460325600,
      "human_date_start":"11 Apr 2016",
      "human_date_end":"11 Apr 2016"
   },
   {  
      "id":"20160412_DevDay",
      "name":"DevDay",
      "description":"Description: DevDay",
      "technologies":"Android",
      "link":"http://devday.de/",
      "attendees":350,
      "country":"Germany",
      "city":"Dresden",
      "timestamp_start":1460412000,
      "timestamp_end":1460412000,
      "human_date_start":"12 Apr 2016",
      "human_date_end":"12 Apr 2016"
   },
   {  
      "id":"20160413_WeAreDevelopers",
      "name":"WeAreDevelopers",
      "description":"Description: WeAreDevelopers",
      "technologies":"Android, Other Google Technology",
      "link":"https://goo.gl/4uIocu",
      "attendees":500,
      "country":"Austria",
      "city":"Vienna",
      "timestamp_start":1460498400,
      "timestamp_end":1460498400,
      "human_date_start":"13 Apr 2016",
      "human_date_end":"13 Apr 2016"
   },
   {  
      "id":"20160418_Jax2016",
      "name":"Jax 2016",
      "description":"Description: Jax 2016",
      "technologies":"Android",
      "link":"https://jax.de/",
      "attendees":1500,
      "country":"Germany",
      "city":"Mainz",
      "timestamp_start":1460930400,
      "timestamp_end":1460930400,
      "human_date_start":"18 Apr 2016",
      "human_date_end":"18 Apr 2016"
   },
   {  
      "id":"20160418_QuoVadis",
      "name":"Quo Vadis",
      "description":"Description: Quo Vadis",
      "technologies":"Play Games",
      "link":"http://qvconf.com/",
      "attendees":3000,
      "country":"Germany",
      "city":"Berlin",
      "timestamp_start":1460930400,
      "timestamp_end":1460930400,
      "human_date_start":"18 Apr 2016",
      "human_date_end":"18 Apr 2016"
   },
   {  
      "id":"20160420_BigdataCon",
      "name":"Big data Con",
      "description":"Description: Big data Con",
      "technologies":"Cloud",
      "link":"http://bigdatacon.de/",
      "attendees":1500,
      "country":"Germany",
      "city":"Mainz",
      "timestamp_start":1461103200,
      "timestamp_end":1461103200,
      "human_date_start":"20 Apr 2016",
      "human_date_end":"20 Apr 2016"
   },
   {  
      "id":"20160420_appsworld",
      "name":"appsworld",
      "description":"Description: appsworld",
      "technologies":"Android",
      "link":"http://germany.apps-world.net/",
      "attendees":6000,
      "country":"Germany",
      "city":"Berlin",
      "timestamp_start":1461103200,
      "timestamp_end":1461103200,
      "human_date_start":"20 Apr 2016",
      "human_date_end":"20 Apr 2016"
   },
   {  
      "id":"20160421_MCE3",
      "name":"MCE3",
      "description":"Description: MCE3",
      "technologies":"Android",
      "link":"http://mceconf.com/index.html",
      "attendees":700,
      "country":"Poland",
      "city":"Warsaw",
      "timestamp_start":1461189600,
      "timestamp_end":1461189600,
      "human_date_start":"21 Apr 2016",
      "human_date_end":"21 Apr 2016"
   },
   {  
      "id":"20160421_Mix-IT",
      "name":"Mix-IT",
      "description":"Description: Mix-IT",
      "technologies":"Cloud, Other Google Technology",
      "link":"https://goo.gl/qkWioi",
      "attendees":1300,
      "country":"France",
      "city":"Lyon",
      "timestamp_start":1461189600,
      "timestamp_end":1461189600,
      "human_date_start":"21 Apr 2016",
      "human_date_end":"21 Apr 2016"
   },
   {  
      "id":"20160424_DroidconMadrid",
      "name":"Droidcon Madrid",
      "description":"Description: Droidcon Madrid",
      "technologies":"Android",
      "link":"http://es.droidcon.com/",
      "attendees":"",
      "country":"Spain",
      "city":"Madrid",
      "timestamp_start":1461448800,
      "timestamp_end":1461448800,
      "human_date_start":"24 Apr 2016",
      "human_date_end":"24 Apr 2016"
   },
   {  
      "id":"20160425_AppBuildersSwitzerland",
      "name":"App Builders Switzerland",
      "description":"Description: App Builders Switzerland",
      "technologies":"Android",
      "link":"appbuilders.ch",
      "attendees":350,
      "country":"Switzerland",
      "city":"Zurich",
      "timestamp_start":1461535200,
      "timestamp_end":1461535200,
      "human_date_start":"25 Apr 2016",
      "human_date_end":"25 Apr 2016"
   },
   {  
      "id":"20160428_M2MWorldcongress",
      "name":"M2M World congress",
      "description":"Description: M2M World congress",
      "technologies":"",
      "link":"2M World congres",
      "attendees":"",
      "country":"UK",
      "city":"London",
      "timestamp_start":1461794400,
      "timestamp_end":1461794400,
      "human_date_start":"28 Apr 2016",
      "human_date_end":"28 Apr 2016"
   },
   {  
      "id":"20160502_re:publica",
      "name":"re:publica",
      "description":"Description: re:publica",
      "technologies":"IoT",
      "link":"https://re-publica.de/",
      "attendees":3100,
      "country":"Germany",
      "city":"Berlin",
      "timestamp_start":1462140000,
      "timestamp_end":1462140000,
      "human_date_start":"2 May 2016",
      "human_date_end":"2 May 2016"
   },
   {  
      "id":"20160509_BeyondTellerrand",
      "name":"Beyond Tellerrand",
      "description":"Description: Beyond Tellerrand",
      "technologies":"Android",
      "link":"https://beyondtellerrand.com/",
      "attendees":450,
      "country":"Germany",
      "city":"D端sseldorf",
      "timestamp_start":1462744800,
      "timestamp_end":1462744800,
      "human_date_start":"9 May 2016",
      "human_date_end":"9 May 2016"
   },
   {  
      "id":"20160511_CodemotionAmsterdam",
      "name":"Codemotion Amsterdam",
      "description":"Description: Codemotion Amsterdam",
      "technologies":"Android",
      "link":"amsterdam2016.codemotionworld.com/",
      "attendees":800,
      "country":"Netherlands",
      "city":"Amsterdam",
      "timestamp_start":1462917600,
      "timestamp_end":1462917600,
      "human_date_start":"11 May 2016",
      "human_date_end":"11 May 2016"
   },
   {  
      "id":"20160518_InfoShare",
      "name":"InfoShare",
      "description":"Description: InfoShare",
      "technologies":"Mobile Web (Create/Make your website mobile friendly)",
      "link":"https://infoshare.pl/",
      "attendees":5000,
      "country":"Poland",
      "city":"Gdansk",
      "timestamp_start":1463522400,
      "timestamp_end":1463522400,
      "human_date_start":"18 May 2016",
      "human_date_end":"18 May 2016"
   },
   {  
      "id":"20160518_Kamailioworld",
      "name":"Kamailioworld",
      "description":"Description: Kamailioworld",
      "technologies":"Other Google Technology",
      "link":"https://www.kamailioworld.com/k04/",
      "attendees":150,
      "country":"Germany",
      "city":"Berlin",
      "timestamp_start":1463522400,
      "timestamp_end":1463522400,
      "human_date_start":"18 May 2016",
      "human_date_end":"18 May 2016"
   },
   {  
      "id":"20160518_NordicGameConference",
      "name":"Nordic Game Conference",
      "description":"Description: Nordic Game Conference",
      "technologies":"",
      "link":"http://conf.nordicgame.com/",
      "attendees":2000,
      "country":"Netherlands",
      "city":"Slagthuset",
      "timestamp_start":1463522400,
      "timestamp_end":1463522400,
      "human_date_start":"18 May 2016",
      "human_date_end":"18 May 2016"
   },
   {  
      "id":"20160522_UIKonf",
      "name":"UIKonf",
      "description":"Description: UIKonf",
      "technologies":"iOS",
      "link":"http://www.uikonf.com/",
      "attendees":200,
      "country":"Germany",
      "city":"Berlin",
      "timestamp_start":1463868000,
      "timestamp_end":1463868000,
      "human_date_start":"22 May 2016",
      "human_date_end":"22 May 2016"
   },
   {  
      "id":"20160524_PioneersFestivalVienna",
      "name":"Pioneers Festival Vienna",
      "description":"Description: Pioneers Festival Vienna",
      "technologies":"Android",
      "link":"https://pioneers.io/festival2016/",
      "attendees":2500,
      "country":"Austria",
      "city":"Vienna",
      "timestamp_start":1464040800,
      "timestamp_end":1464040800,
      "human_date_start":"24 May 2016",
      "human_date_end":"24 May 2016"
   },
   {  
      "id":"20160527_UpFront",
      "name":"UpFront",
      "description":"Description: UpFront",
      "technologies":"",
      "link":"not yet announced",
      "attendees":"",
      "country":"UK",
      "city":"Manchester",
      "timestamp_start":1464300000,
      "timestamp_end":1464300000,
      "human_date_start":"27 May 2016",
      "human_date_end":"27 May 2016"
   },
   {  
      "id":"20160531_StrataConf",
      "name":"Strata Conf",
      "description":"Description: Strata Conf",
      "technologies":"Cloud",
      "link":"http://strataconf.com/big-data-conference-uk-2015",
      "attendees":1200,
      "country":"UK",
      "city":"London",
      "timestamp_start":1464645600,
      "timestamp_end":1464645600,
      "human_date_start":"31 May 2016",
      "human_date_end":"31 May 2016"
   },
   {  
      "id":"20160601_B2BRocks",
      "name":"B2B Rocks",
      "description":"Description: B2B Rocks",
      "technologies":"Other Google Technology, Open technologies (non-google)",
      "link":"https://goo.gl/7EXSlv",
      "attendees":200,
      "country":"France",
      "city":"Paris",
      "timestamp_start":1464732000,
      "timestamp_end":1464732000,
      "human_date_start":"1 Jun 2016",
      "human_date_end":"1 Jun 2016"
   },
   {  
      "id":"20160605_BerlinBuzzwords",
      "name":"Berlin Buzzwords",
      "description":"Description: Berlin Buzzwords",
      "technologies":"Cloud",
      "link":"https://berlinbuzzwords.de/about",
      "attendees":600,
      "country":"Germany",
      "city":"Berlin",
      "timestamp_start":1465077600,
      "timestamp_end":1465077600,
      "human_date_start":"5 Jun 2016",
      "human_date_end":"5 Jun 2016"
   },
   {  
      "id":"20160607_WebWeekBerlin",
      "name":"Web Week Berlin",
      "description":"Description: Web Week Berlin",
      "technologies":"Mobile Web (Create/Make your website mobile friendly)",
      "link":"http://berlinwebweek.de/about/?lang=en",
      "attendees":20000,
      "country":"Germany",
      "city":"Berlin",
      "timestamp_start":1465250400,
      "timestamp_end":1465250400,
      "human_date_start":"7 Jun 2016",
      "human_date_end":"7 Jun 2016"
   },
   {  
      "id":"20160608_DevOxxUK",
      "name":"DevOxx UK",
      "description":"Description: DevOxx UK",
      "technologies":"Cloud",
      "link":"http://lanyrd.com/2016/devoxxuk/",
      "attendees":1200,
      "country":"UK",
      "city":"London",
      "timestamp_start":1465336800,
      "timestamp_end":1465336800,
      "human_date_start":"8 Jun 2016",
      "human_date_end":"8 Jun 2016"
   },
   {  
      "id":"20160614_GOTOAmsterdam2016",
      "name":"GOTO Amsterdam 2016",
      "description":"Description: GOTO Amsterdam 2016",
      "technologies":"Cloud",
      "link":"https://goo.gl/gvJXjs",
      "attendees":100,
      "country":"Netherlands",
      "city":"Amsterdam",
      "timestamp_start":1465855200,
      "timestamp_end":1465855200,
      "human_date_start":"14 Jun 2016",
      "human_date_end":"14 Jun 2016"
   },
   {  
      "id":"20160615_DroidconBerlin",
      "name":"Droidcon Berlin",
      "description":"Description: Droidcon Berlin",
      "technologies":"Android",
      "link":"http://de.droidcon.com/en",
      "attendees":1000,
      "country":"Germany",
      "city":"Berlin",
      "timestamp_start":1465941600,
      "timestamp_end":1465941600,
      "human_date_start":"15 Jun 2016",
      "human_date_end":"15 Jun 2016"
   },
   {  
      "id":"20160629_ReWorkMachineIntelligenceSummit",
      "name":"ReWork Machine Intelligence Summit",
      "description":"Description: ReWork Machine Intelligence Summit",
      "technologies":"IoT",
      "link":"https://re-work.co/events/machine-intelligence-berlin-2016",
      "attendees":250,
      "country":"Germany",
      "city":"Berlin",
      "timestamp_start":1467151200,
      "timestamp_end":1467151200,
      "human_date_start":"29 Jun 2016",
      "human_date_end":"29 Jun 2016"
   },
   {  
      "id":"20160815_GDCEurope",
      "name":"GDC Europe",
      "description":"Description: GDC Europe",
      "technologies":"Play Games",
      "link":"http://www.gdceurope.com/aboutgdc/",
      "attendees":2800,
      "country":"Germany",
      "city":"Cologne",
      "timestamp_start":1471212000,
      "timestamp_end":1471212000,
      "human_date_start":"15 Aug 2016",
      "human_date_end":"15 Aug 2016"
   },
   {  
      "id":"20160817_Gamescom",
      "name":"Gamescom",
      "description":"Description: Gamescom",
      "technologies":"Play Games",
      "link":"http://www.gamescom-cologne.com/gamescom/index-9.php",
      "attendees":345000,
      "country":"Germany",
      "city":"Cologne",
      "timestamp_start":1471384800,
      "timestamp_end":1471384800,
      "human_date_start":"17 Aug 2016",
      "human_date_end":"17 Aug 2016"
   },
   {  
      "id":"20160901_AndroidSummit",
      "name":"Android Summit",
      "description":"Description: Android Summit",
      "technologies":"Android",
      "link":"androidsummit.org/",
      "attendees":150,
      "country":"Austria",
      "city":"Vienna",
      "timestamp_start":1472680800,
      "timestamp_end":1472680800,
      "human_date_start":"1 Sep 2016",
      "human_date_end":"1 Sep 2016"
   },
   {  
      "id":"20160901_DroidconGreece",
      "name":"Droidcon Greece",
      "description":"Description: Droidcon Greece",
      "technologies":"Android",
      "link":"droidcon.gr",
      "attendees":70,
      "country":"Greece",
      "city":"Thessaloniki",
      "timestamp_start":1472680800,
      "timestamp_end":1472680800,
      "human_date_start":"1 Sep 2016",
      "human_date_end":"1 Sep 2016"
   },
   {  
      "id":"20160905_ESOCC2016",
      "name":"ESOCC 2016",
      "description":"Description: ESOCC 2016",
      "technologies":"Cloud",
      "link":"https://goo.gl/DSbdLS",
      "attendees":200,
      "country":"Austria",
      "city":"Vienna",
      "timestamp_start":1473026400,
      "timestamp_end":1473026400,
      "human_date_start":"5 Sep 2016",
      "human_date_end":"5 Sep 2016"
   },
   {  
      "id":"20160914_DMEXCO",
      "name":"DMEXCO",
      "description":"Description: DMEXCO",
      "technologies":"Ads General",
      "link":"http://dmexco.de/en/Home.html",
      "attendees":43000,
      "country":"Germany",
      "city":"Cologne",
      "timestamp_start":1473804000,
      "timestamp_end":1473804000,
      "human_date_start":"14 Sep 2016",
      "human_date_end":"14 Sep 2016"
   },
   {  
      "id":"20160916_HackZurich",
      "name":"Hack Zurich",
      "description":"Description: Hack Zurich",
      "technologies":"Android",
      "link":"http://hackzurich.com/",
      "attendees":500,
      "country":"Switzerland",
      "city":"Zurich",
      "timestamp_start":1473976800,
      "timestamp_end":1473976800,
      "human_date_start":"16 Sep 2016",
      "human_date_end":"16 Sep 2016"
   },
   {  
      "id":"20160925_Bits&Pretzels",
      "name":"Bits & Pretzels",
      "description":"Description: Bits & Pretzels",
      "technologies":"Other Google Technology",
      "link":"https://www.bitsandpretzels.com/",
      "attendees":3600,
      "country":"Germany",
      "city":"Munich",
      "timestamp_start":1474754400,
      "timestamp_end":1474754400,
      "human_date_start":"25 Sep 2016",
      "human_date_end":"25 Sep 2016"
   },
   {  
      "id":"20161010_DotGo",
      "name":"DotGo",
      "description":"Description: DotGo",
      "technologies":"Other Google Technology",
      "link":"https://goo.gl/KAaT8U",
      "attendees":800,
      "country":"France",
      "city":"Paris",
      "timestamp_start":1476050400,
      "timestamp_end":1476050400,
      "human_date_start":"10 Oct 2016",
      "human_date_end":"10 Oct 2016"
   },
   {  
      "id":"20161023_WebTechConference",
      "name":"WebTech Conference",
      "description":"Description: WebTech Conference",
      "technologies":"Mobile Web (Create/Make your website mobile friendly)",
      "link":"https://webtechcon.de/2015/",
      "attendees":"",
      "country":"Germany",
      "city":"Munich",
      "timestamp_start":1477173600,
      "timestamp_end":1477173600,
      "human_date_start":"23 Oct 2016",
      "human_date_end":"23 Oct 2016"
   },
   {  
      "id":"20161024_CodemotionBerlin",
      "name":"Codemotion Berlin",
      "description":"Description: Codemotion Berlin",
      "technologies":"Android",
      "link":"http://berlin2015.codemotionworld.com/",
      "attendees":400,
      "country":"Germany",
      "city":"Berlin",
      "timestamp_start":1477260000,
      "timestamp_end":1477260000,
      "human_date_start":"24 Oct 2016",
      "human_date_end":"24 Oct 2016"
   },
   {  
      "id":"20161025_ng-europe",
      "name":"ng-europe",
      "description":"Description: ng-europe",
      "technologies":"Open technologies (non-google)",
      "link":"https://goo.gl/7nnrBO",
      "attendees":500,
      "country":"France",
      "city":"Paris",
      "timestamp_start":1477346400,
      "timestamp_end":1477346400,
      "human_date_start":"25 Oct 2016",
      "human_date_end":"25 Oct 2016"
   },
   {  
      "id":"20161101_BigAndroidBBQEurope",
      "name":"Big Android BBQ Europe",
      "description":"Description: Big Android BBQ Europe",
      "technologies":"Android",
      "link":"babbq.nl/",
      "attendees":"",
      "country":"Netherlands",
      "city":"Amsterdam",
      "timestamp_start":1477954800,
      "timestamp_end":1477954800,
      "human_date_start":"1 Nov 2016",
      "human_date_end":"1 Nov 2016"
   },
   {  
      "id":"20161101_CodemotionMadrid",
      "name":"Codemotion Madrid",
      "description":"Description: Codemotion Madrid",
      "technologies":"Android",
      "link":"codemotion.es",
      "attendees":2100,
      "country":"Spain",
      "city":"Madrid",
      "timestamp_start":1477954800,
      "timestamp_end":1477954800,
      "human_date_start":"1 Nov 2016",
      "human_date_end":"1 Nov 2016"
   },
   {  
      "id":"20161101_CodemotionMilan2016",
      "name":"Codemotion Milan 2016",
      "description":"Description: Codemotion Milan 2016",
      "technologies":"Android",
      "link":"milan2016.codemotionworld.com",
      "attendees":2000,
      "country":"Italy",
      "city":"Milan",
      "timestamp_start":1477954800,
      "timestamp_end":1477954800,
      "human_date_start":"1 Nov 2016",
      "human_date_end":"1 Nov 2016"
   },
   {  
      "id":"20161101_DevFestGreece",
      "name":"DevFest Greece",
      "description":"Description: DevFest Greece",
      "technologies":"Android",
      "link":"devfest.gr",
      "attendees":900,
      "country":"Greece",
      "city":"Heraklion",
      "timestamp_start":1477954800,
      "timestamp_end":1477954800,
      "human_date_start":"1 Nov 2016",
      "human_date_end":"1 Nov 2016"
   },
   {  
      "id":"20161101_DevFestNantes",
      "name":"DevFest Nantes",
      "description":"Description: DevFest Nantes",
      "technologies":"Android",
      "link":"devfest.gdgnantes.com/",
      "attendees":500,
      "country":"France",
      "city":"Nantes",
      "timestamp_start":1477954800,
      "timestamp_end":1477954800,
      "human_date_start":"1 Nov 2016",
      "human_date_end":"1 Nov 2016"
   },
   {  
      "id":"20161101_DroidconParis",
      "name":"Droidcon Paris",
      "description":"Description: Droidcon Paris",
      "technologies":"Android",
      "link":"droidcon.fr",
      "attendees":500,
      "country":"France",
      "city":"Paris",
      "timestamp_start":1477954800,
      "timestamp_end":1477954800,
      "human_date_start":"1 Nov 2016",
      "human_date_end":"1 Nov 2016"
   },
   {  
      "id":"20161103_FokusFUSECOForum",
      "name":"Fokus FUSECO Forum",
      "description":"Description: Fokus FUSECO Forum",
      "technologies":"IoT",
      "link":"https://www.fokus.fraunhofer.de/fuseco-forum-2016",
      "attendees":250,
      "country":"Germany",
      "city":"Berlin",
      "timestamp_start":1478127600,
      "timestamp_end":1478127600,
      "human_date_start":"3 Nov 2016",
      "human_date_end":"3 Nov 2016"
   },
   {  
      "id":"20161107_BeyondTellerrand",
      "name":"Beyond Tellerrand",
      "description":"Description: Beyond Tellerrand",
      "technologies":"Android",
      "link":"https://beyondtellerrand.com/",
      "attendees":500,
      "country":"Germany",
      "city":"Berlin",
      "timestamp_start":1478473200,
      "timestamp_end":1478473200,
      "human_date_start":"7 Nov 2016",
      "human_date_end":"7 Nov 2016"
   },
   {  
      "id":"20161117_CodemotionMilan",
      "name":"Codemotion Milan",
      "description":"Description: Codemotion Milan",
      "technologies":"Android, Firebase",
      "link":"https://goo.gl/xzxDDL",
      "attendees":2000,
      "country":"Italy",
      "city":"Milan",
      "timestamp_start":1479337200,
      "timestamp_end":1479337200,
      "human_date_start":"17 Nov 2016",
      "human_date_end":"17 Nov 2016"
   },
   {  
      "id":"20161124_CodemotionES",
      "name":"Codemotion ES",
      "description":"Description: Codemotion ES",
      "technologies":"Android, Cloud, Firebase, Mobile Web ( Create/Make your website mobile friendly)",
      "link":"https://goo.gl/jbJijr",
      "attendees":2000,
      "country":"Spain",
      "city":"Madrid",
      "timestamp_start":1479942000,
      "timestamp_end":1479942000,
      "human_date_start":"24 Nov 2016",
      "human_date_end":"24 Nov 2016"
   },
   {  
      "id":"20161201_MakeMunich",
      "name":"Make Munich",
      "description":"Description: Make Munich",
      "technologies":"Other Google Technology",
      "link":"https://goo.gl/vZUVCv",
      "attendees":7500,
      "country":"Germany",
      "city":"Munich",
      "timestamp_start":1480546800,
      "timestamp_end":1480546800,
      "human_date_start":"1 Dec 2016",
      "human_date_end":"1 Dec 2016"
   }
]